odoo/addons/stock_scanner_location_info/README.rst
odoo/addons/stock_scanner_location_info/__init__.py
odoo/addons/stock_scanner_location_info/__manifest__.py
odoo/addons/stock_scanner_location_info/data/Location_informations/Location_informations.scenario
odoo/addons/stock_scanner_location_info/data/Location_informations/scanner_scenario_step_location_informations_informations_display.py
odoo/addons/stock_scanner_location_info/data/Location_informations/scanner_scenario_step_location_informations_location_selection.py
odoo/addons/stock_scanner_location_info/data/Location_informations/scanner_scenario_step_location_informations_unknown_location.py
odoo/addons/stock_scanner_location_info/i18n/es.po
odoo/addons/stock_scanner_location_info/i18n/stock_scanner_location_info.pot
odoo/addons/stock_scanner_location_info/images/scenario.png
odoo/addons/stock_scanner_location_info/readme/CONTRIBUTORS.rst
odoo/addons/stock_scanner_location_info/readme/DESCRIPTION.rst
odoo/addons/stock_scanner_location_info/readme/INSTALL.rst
odoo/addons/stock_scanner_location_info/static/description/icon.png
odoo/addons/stock_scanner_location_info/static/description/index.html
odoo11_addon_stock_scanner_location_info-11.0.1.0.0.99.dev8.dist-info/METADATA
odoo11_addon_stock_scanner_location_info-11.0.1.0.0.99.dev8.dist-info/WHEEL
odoo11_addon_stock_scanner_location_info-11.0.1.0.0.99.dev8.dist-info/top_level.txt
odoo11_addon_stock_scanner_location_info-11.0.1.0.0.99.dev8.dist-info/RECORD
